global_identity/__init__.py
global_identity/global_identity.py
stone_co_global_identity-1.2.1.dist-info/METADATA
stone_co_global_identity-1.2.1.dist-info/RECORD
stone_co_global_identity-1.2.1.dist-info/WHEEL
stone_co_global_identity-1.2.1.dist-info/top_level.txt
stone_co_global_identity-1.2.1.dist-info/zip-safe
tests/unit/__init__.py
tests/unit/test_global_identity.py
