Metadata-Version: 2.1
Name: stone-co-global-identity
Version: 1.2.1
Summary: Global Identity Authentication PIP
Home-page: https://github.com/stone-payments/globalidentity-python
Author: Customer Satisfaction
Author-email: jfreitas@stone.com.br
License: MIT License
Keywords: global identity
Platform: UNKNOWN
Classifier: Topic :: System :: Systems Administration :: Authentication/Directory
Requires-Dist: requests
Requires-Dist: pytest
Requires-Dist: setuptools
Requires-Dist: urllib3
Requires-Dist: certifi
Requires-Dist: idna
